django_taxi/__init__.py
django_taxi/admin.py
django_taxi/apps.py
django_taxi/fields.py
django_taxi/migrations/0001_initial.py
django_taxi/migrations/__init__.py
django_taxi/mixins.py
django_taxi/models.py
django_taxi-0.1.0.dist-info/LICENSE.md
django_taxi-0.1.0.dist-info/WHEEL
django_taxi-0.1.0.dist-info/METADATA
django_taxi-0.1.0.dist-info/RECORD
